<annotation>
	<folder>images</folder>
	<filename>111.jpg</filename>
	<path>C:\Users\omar\Downloads\Recycling_ML\object_detection_demo\data\images\111.jpg</path>
	<source>
		<database>Unknown</database>
	</source>
	<size>
		<width>800</width>
		<height>600</height>
		<depth>3</depth>
	</size>
	<segmented>0</segmented>
	<object>
		<name>Glass bottle</name>
		<pose>Unspecified</pose>
		<truncated>0</truncated>
		<difficult>0</difficult>
		<bndbox>
			<xmin>66</xmin>
			<ymin>30</ymin>
			<xmax>376</xmax>
			<ymax>591</ymax>
		</bndbox>
	</object>
	<object>
		<name>Glass bottle</name>
		<pose>Unspecified</pose>
		<truncated>1</truncated>
		<difficult>0</difficult>
		<bndbox>
			<xmin>331</xmin>
			<ymin>1</ymin>
			<xmax>631</xmax>
			<ymax>539</ymax>
		</bndbox>
	</object>
	<object>
		<name>Glass bottle</name>
		<pose>Unspecified</pose>
		<truncated>1</truncated>
		<difficult>0</difficult>
		<bndbox>
			<xmin>607</xmin>
			<ymin>132</ymin>
			<xmax>800</xmax>
			<ymax>591</ymax>
		</bndbox>
	</object>
</annotation>
