<annotation>
	<folder>google_images_soda_cans_dataset</folder>
	<filename>Soda_Can_368.jpg</filename>
	<path>C:\Users\omar\Downloads\ML_datasets\google_images_soda_cans_dataset\Soda_Can_368.jpg</path>
	<source>
		<database>Unknown</database>
	</source>
	<size>
		<width>500</width>
		<height>366</height>
		<depth>3</depth>
	</size>
	<segmented>0</segmented>
	<object>
		<name>Can</name>
		<pose>Unspecified</pose>
		<truncated>0</truncated>
		<difficult>0</difficult>
		<bndbox>
			<xmin>4</xmin>
			<ymin>2</ymin>
			<xmax>496</xmax>
			<ymax>363</ymax>
		</bndbox>
	</object>
</annotation>
